cli/__init__.py
cli/__main__.py
cli/cmd_config.py
cli/cmd_pipeline.py
controller/__init__.py
controller/controller.py
util/__init__.py
util/common_utils.py
util/config_tools.py
util/constant.py
util/container.py
util/db_artifact.py
util/db_mongo.py
util/model.py
util/repo_manager.py
util/yaml_parser.py
t4_cicd-0.2.1.dist-info/entry_points.txt
t4_cicd-0.2.1.dist-info/LICENSE
t4_cicd-0.2.1.dist-info/METADATA
t4_cicd-0.2.1.dist-info/WHEEL
t4_cicd-0.2.1.dist-info/RECORD
